RTL/adder_buffer.v
// this is an accumulator module 
module adder_buffer(

input [255:0] input_1,
input reset,
input clock,
input systolic_done,

output reg accumulator_done,
output reg [255:0] out

);

reg [15:0]update_value[15:0];
reg [5:0] count;

always @(posedge systolic_done)begin //if systolic finished counting, then the buffer will update its value

update_value[0] <= update_value[0]+ input_1[255:240];
update_value[1] <= update_value[1]+ input_1[255-16*1:255-16*1-15];
update_value[2] <= update_value[2]+ input_1[255-16*2:255-16*2-15];
update_value[3] <= update_value[3]+ input_1[255-16*3:255-16*3-15];
update_value[4] <= update_value[4]+ input_1[255-16*4:255-16*4-15];
update_value[5] <= update_value[5]+ input_1[255-16*5:255-16*5-15];
update_value[6] <= update_value[6]+ input_1[255-16*6:255-16*6-15];
update_value[7] <= update_value[7]+ input_1[255-16*7:255-16*7-15];
update_value[8] <= update_value[8]+ input_1[255-16*8:255-16*8-15];
update_value[9] <= update_value[9]+ input_1[255-16*9:255-16*9-15];
update_value[10] <= update_value[10]+ input_1[255-16*10:255-16*10-15];
update_value[11] <= update_value[11]+ input_1[255-16*11:255-16*11-15];
update_value[12] <= update_value[12]+ input_1[255-16*12:255-16*12-15];
update_value[13] <= update_value[13]+ input_1[255-16*13:255-16*13-15];
update_value[14] <= update_value[14]+ input_1[255-16*14:255-16*14-15];
update_value[15] <= update_value[15]+ input_1[255-16*15:255-16*15-15];


end

always @(posedge systolic_done or posedge reset) begin
	if(reset) begin
		accumulator_done <= 0;
		count <= 0;
        update_value[0] <= 'h0000;
        update_value[1] <= 'h0000;
        update_value[2] <= 'h0000;
        update_value[3] <= 'h0000;
        update_value[4] <= 'h0000;
        update_value[5] <= 'h0000;
        update_value[6] <= 'h0000;
        update_value[7] <= 'h0000;
        update_value[8] <= 'h0000;
        update_value[9] <= 'h0000;
        update_value[10] <= 'h0000; 
        update_value[11] <= 'h0000;
        update_value[12] <= 'h0000;
        update_value[13] <= 'h0000;
        update_value[14] <= 'h0000;
        update_value[15] <= 'h0000;
        out <=  'h0000000000000000000000000000000000000000000000000000000000000000;


	end
	else begin
		if(count == 63) begin
			accumulator_done <= 1;
            out <= {update_value[0],update_value[1],update_value[2],update_value[3],update_value[4],update_value[5],update_value[6],update_value[7],update_value[8],update_value[9],update_value[10],update_value[11],update_value[12],update_value[13],update_value[14],update_value[15]};
			count <= 0;
		end
		else begin
			accumulator_done <= 0;
			count <= count + 1;
		end
	end	
end




endmodule

Testbench/RTL_tb/adder_buffer_tb.v
`include "adder_buffer.v"

module adder_buffer_tb;

reg [255:0] test_input;
reg reset;
reg clock;
reg systolic_done;
wire accumulator_done;
wire [255:0] out;

adder_buffer add_0(

.input_1(test_input),
.reset(reset),
.clock(clock),
.systolic_done(systolic_done),
.accumulator_done(accumulator_done),
.out(out)
);

initial begin
reset <= 1;
systolic_done <= 0;
#3
reset <= 0;
test_input <= 'h000400E800C9008D00F400D10017000C00EA001300EB00BD010000FA00DD0060;
#8
test_input <= 'h000400E800C9008D00F400D10017000C00EA001300EB00BD010000FA00DD0060;
#13
test_input <= 'h0000000000000000000000000000000000000000000000000000000000000000;


end

initial begin
	repeat(133)
		#5 systolic_done <= ~systolic_done;
end


initial begin
	$dumpfile("wave_adder_buffer.vcd");
	$dumpvars(0, adder_buffer_tb);
end





endmodule

Testbench/RTL_tb/wave_adder_buffer.vcd
$date
	Sat Dec 28 14:09:19 2024
$end
$version
	Icarus Verilog
$end
$timescale
	1s
$end
$scope module adder_buffer_tb $end
$var wire 256 ! out [255:0] $end
$var wire 1 " accumulator_done $end
$var reg 1 # clock $end
$var reg 1 $ reset $end
$var reg 1 % systolic_done $end
$var reg 256 & test_input [255:0] $end
$scope module add_0 $end
$var wire 1 # clock $end
$var wire 256 ' input_1 [255:0] $end
$var wire 1 $ reset $end
$var wire 1 % systolic_done $end
$var reg 1 " accumulator_done $end
$var reg 6 ( count [5:0] $end
$var reg 256 ) out [255:0] $end
$upscope $end
$upscope $end
$enddefinitions $end
$comment Show the parameter values. $end
$dumpall
$end
#0
$dumpvars
b0 )
b0 (
bx '
bx &
0%
1$
x#
0"
b0 !
$end
#3
b100000000001110100000000000110010010000000010001101000000001111010000000000110100010000000000010111000000000000110000000000111010100000000000010011000000001110101100000000101111010000000100000000000000001111101000000000110111010000000001100000 &
b100000000001110100000000000110010010000000010001101000000001111010000000000110100010000000000010111000000000000110000000000111010100000000000010011000000001110101100000000101111010000000100000000000000001111101000000000110111010000000001100000 '
0$
#5
b1 (
1%
#10
0%
#15
b10 (
1%
#20
0%
#24
b0 &
b0 '
#25
b11 (
1%
#30
0%
#35
b100 (
1%
#40
0%
#45
b101 (
1%
#50
0%
#55
b110 (
1%
#60
0%
#65
b111 (
1%
#70
0%
#75
b1000 (
1%
#80
0%
#85
b1001 (
1%
#90
0%
#95
b1010 (
1%
#100
0%
#105
b1011 (
1%
#110
0%
#115
b1100 (
1%
#120
0%
#125
b1101 (
1%
#130
0%
#135
b1110 (
1%
#140
0%
#145
b1111 (
1%
#150
0%
#155
b10000 (
1%
#160
0%
#165
b10001 (
1%
#170
0%
#175
b10010 (
1%
#180
0%
#185
b10011 (
1%
#190
0%
#195
b10100 (
1%
#200
0%
#205
b10101 (
1%
#210
0%
#215
b10110 (
1%
#220
0%
#225
b10111 (
1%
#230
0%
#235
b11000 (
1%
#240
0%
#245
b11001 (
1%
#250
0%
#255
b11010 (
1%
#260
0%
#265
b11011 (
1%
#270
0%
#275
b11100 (
1%
#280
0%
#285
b11101 (
1%
#290
0%
#295
b11110 (
1%
#300
0%
#305
b11111 (
1%
#310
0%
#315
b100000 (
1%
#320
0%
#325
b100001 (
1%
#330
0%
#335
b100010 (
1%
#340
0%
#345
b100011 (
1%
#350
0%
#355
b100100 (
1%
#360
0%
#365
b100101 (
1%
#370
0%
#375
b100110 (
1%
#380
0%
#385
b100111 (
1%
#390
0%
#395
b101000 (
1%
#400
0%
#405
b101001 (
1%
#410
0%
#415
b101010 (
1%
#420
0%
#425
b101011 (
1%
#430
0%
#435
b101100 (
1%
#440
0%
#445
b101101 (
1%
#450
0%
#455
b101110 (
1%
#460
0%
#465
b101111 (
1%
#470
0%
#475
b110000 (
1%
#480
0%
#485
b110001 (
1%
#490
0%
#495
b110010 (
1%
#500
0%
#505
b110011 (
1%
#510
0%
#515
b110100 (
1%
#520
0%
#525
b110101 (
1%
#530
0%
#535
b110110 (
1%
#540
0%
#545
b110111 (
1%
#550
0%
#555
b111000 (
1%
#560
0%
#565
b111001 (
1%
#570
0%
#575
b111010 (
1%
#580
0%
#585
b111011 (
1%
#590
0%
#595
b111100 (
1%
#600
0%
#605
b111101 (
1%
#610
0%
#615
b111110 (
1%
#620
0%
#625
b111111 (
1%
#630
0%
#635
b0 (
b1000000000011101000000000001100100100000000100011010000000011110100000000001101000100000000000101110000000000001100000000001110101000000000000100110000000011101011000000001011110100000001000000000000000011111010000000001101110100000000011000000 !
b1000000000011101000000000001100100100000000100011010000000011110100000000001101000100000000000101110000000000001100000000001110101000000000000100110000000011101011000000001011110100000001000000000000000011111010000000001101110100000000011000000 )
1"
1%
#640
0%
#645
b1 (
0"
1%
#650
0%
#655
b10 (
1%
#660
0%
#665
b11 (
1%
